require_package/__init__.py
require_package/main.py
require_package-0.0.1.dist-info/METADATA
require_package-0.0.1.dist-info/WHEEL
require_package-0.0.1.dist-info/licenses/LICENCE.txt
require_package-0.0.1.dist-info/RECORD
