Metadata-Version: 2.1
Name: require-package
Version: 0.0.1
Summary: Provides one-time installation of Python package
Project-URL: Homepage, https://github.com/mariownyou/python-require-package
Project-URL: Bug Tracker, https://github.com/mariownyou/python-require-package/issues
Author-email: Leva Ginzburg <smj510black@gmail.com>
License-File: LICENCE.txt
Classifier: License :: OSI Approved :: MIT License
Classifier: Operating System :: OS Independent
Classifier: Programming Language :: Python :: 3
Requires-Python: >=3.7
